{
  "login": "kudsu",
  "id": 31930092,
  "node_id": "MDQ6VXNlcjMxOTMwMDky",
  "avatar_url": "https://avatars3.githubusercontent.com/u/31930092?v=4",
  "gravatar_id": "",
  "url": "https://api.github.com/users/kudsu",
  "html_url": "https://github.com/kudsu",
  "followers_url": "https://api.github.com/users/kudsu/followers",
  "following_url": "https://api.github.com/users/kudsu/following{/other_user}",
  "gists_url": "https://api.github.com/users/kudsu/gists{/gist_id}",
  "starred_url": "https://api.github.com/users/kudsu/starred{/owner}{/repo}",
  "subscriptions_url": "https://api.github.com/users/kudsu/subscriptions",
  "organizations_url": "https://api.github.com/users/kudsu/orgs",
  "repos_url": "https://api.github.com/users/kudsu/repos",
  "events_url": "https://api.github.com/users/kudsu/events{/privacy}",
  "received_events_url": "https://api.github.com/users/kudsu/received_events",
  "type": "User",
  "site_admin": false,
  "name": "Snoopy",
  "company": "三希",
  "blog": "https://www.cnblogs.com/kudsu",
  "location": "河南周口",
  "email": null,
  "hireable": null,
  "bio": "i do.",
  "public_repos": 30,
  "public_gists": 0,
  "followers": 2,
  "following": 1,
  "created_at": "2017-09-13T15:13:06Z",
  "updated_at": "2019-12-12T07:36:48Z"
}